[{"Pressed": "'f'"}, {"Held": "'f'"}, {"Released": "'f'"}, {"Pressed": "'a'"}, {"Held": "'a'"}, {"Held": "'c'"}, {"Released": "'a'"}, {"Released": "'c'"}, {"Pressed": "'e'"}, {"Held": "'e'"}, {"Released": "'e'"}, {"Pressed": "'b'"}, {"Held": "'b'"}, {"Released": "'b'"}, {"Pressed": "'o'"}, {"Held": "'o'"}, {"Released": "'o'"}, {"Pressed": "'o'"}, {"Held": "'o'"}, {"Released": "'o'"}, {"Pressed": "'k'"}, {"Held": "'k'"}, {"Released": "'k'"}, {"Pressed": "Key.space"}, {"Held": "Key.space"}, {"Released": "Key.space"}, {"Pressed": "'l'"}, {"Held": "'l'"}, {"Released": "'l'"}, {"Pressed": "'o'"}, {"Held": "'o'"}, {"Released": "'o'"}, {"Pressed": "'g'"}, {"Held": "'g'"}, {"Released": "'g'"}, {"Pressed": "'i'"}, {"Held": "'i'"}, {"Released": "'i'"}, {"Pressed": "'n'"}, {"Held": "'n'"}, {"Released": "'n'"}, {"Pressed": "Key.space"}, {"Held": "Key.space"}, {"Released": "Key.space"}, {"Pressed": "Key.enter"}, {"Held": "Key.enter"}, {"Released": "Key.enter"}, {"Pressed": "'s'"}, {"Held": "'s'"}, {"Released": "'s'"}, {"Pressed": "'a'"}, {"Held": "'a'"}, {"Released": "'a'"}, {"Pressed": "'i'"}, {"Held": "'i'"}, {"Released": "'i'"}, {"Pressed": "'1'"}, {"Held": "'1'"}, {"Released": "'1'"}, {"Pressed": "'2'"}, {"Held": "'2'"}, {"Released": "'2'"}, {"Pressed": "'3'"}, {"Held": "'3'"}, {"Released": "'3'"}, {"Pressed": "'4'"}, {"Held": "'4'"}, {"Released": "'4'"}, {"Pressed": "'5'"}, {"Held": "'5'"}, {"Released": "'5'"}, {"Pressed": "'g'"}, {"Held": "'g'"}, {"Released": "'g'"}, {"Pressed": "'e'"}, {"Held": "'e'"}, {"Released": "'e'"}, {"Pressed": "'j'"}, {"Held": "'j'"}, {"Released": "'j'"}, {"Pressed": "'r'"}, {"Held": "'r'"}, {"Released": "'r'"}, {"Pressed": "'5'"}, {"Held": "'5'"}, {"Held": "'w'"}, {"Held": "'q'"}, {"Released": "'5'"}, {"Released": "'q'"}, {"Pressed": "'g'"}, {"Held": "'g'"}, {"Released": "'w'"}, {"Released": "'g'"}, {"Pressed": "'h'"}, {"Held": "'h'"}, {"Released": "'h'"}, {"Pressed": "';'"}, {"Held": "';'"}, {"Held": "'d'"}, {"Released": "';'"}, {"Released": "'d'"}]